ghpick/__init__.py
ghpick/cherry.py
ghpick/engine.py
ghpick-1.0.dist-info/DESCRIPTION.rst
ghpick-1.0.dist-info/METADATA
ghpick-1.0.dist-info/metadata.json
ghpick-1.0.dist-info/RECORD
ghpick-1.0.dist-info/top_level.txt
ghpick-1.0.dist-info/WHEEL
