Metadata-Version: 2.0
Name: ghpick
Version: 1.0
Summary: Perform cherry-pick patching with the Github API
Home-page: http://github.com/whiskeyriver/ghpick
Author: Ryan Parr
Author-email: whiskeyriver
License: MIT
Keywords: github githubapi cherry pick cherry-pick cherrypick merge
Platform: UNKNOWN
Requires-Dist: requests (>=2.7.0)
